MANIFEST.in
setup.py
src/trueaccord/__init__.py
src/trueaccord/pants/__init__.py
src/trueaccord/pants/scalapb/__init__.py
src/trueaccord/pants/scalapb/register.py
src/trueaccord/pants/scalapb/targets/__init__.py
src/trueaccord/pants/scalapb/targets/scalapb_library.py
src/trueaccord/pants/scalapb/tasks/__init__.py
src/trueaccord/pants/scalapb/tasks/scalapb_gen.py
src/zr.scalapb.pants.egg-info/PKG-INFO
src/zr.scalapb.pants.egg-info/SOURCES.txt
src/zr.scalapb.pants.egg-info/dependency_links.txt
src/zr.scalapb.pants.egg-info/top_level.txt
src/zr.scalapb.pants.egg-info/zip-safe