Metadata-Version: 1.1
Name: zr.scalapb.pants
Version: 0.1.6
Summary: ScalaPB plugin for Pants
Home-page: https://github.com/zenreach/scalapb-pants
Author: Nikhil Murthy
Author-email: nikhil@zenreach.com
License: Apache License, Version 2.0
Platform: UNKNOWN
Classifier: Intended Audience :: Developers
Classifier: License :: OSI Approved :: Apache Software License
Classifier: Operating System :: OS Independent
Classifier: Programming Language :: Python
